twitter_tap/__init__.py
twitter_tap/filer.py
twitter_tap/tap.py
twitter_tap-2.2.1.dist-info/LICENSE
twitter_tap-2.2.1.dist-info/METADATA
twitter_tap-2.2.1.dist-info/WHEEL
twitter_tap-2.2.1.dist-info/entry_points.txt
twitter_tap-2.2.1.dist-info/top_level.txt
twitter_tap-2.2.1.dist-info/RECORD
