Metadata-Version: 2.1
Name: twitter-tap
Version: 2.2.1
Summary: Collect tweets to a mongoDB using either the Twitter search API or the streaming API.
Home-page: http://janezkranjc.github.io/twitter-tap/
Author: Janez Kranjc
Author-email: janez.kranjc@gmail.com
License: MIT
Platform: UNKNOWN
Classifier: Development Status :: 5 - Production/Stable
Classifier: Intended Audience :: Developers
Classifier: Intended Audience :: Science/Research
Classifier: License :: OSI Approved :: MIT License
Classifier: Topic :: Communications :: Chat
Classifier: Topic :: Internet
Classifier: Topic :: Database
Requires-Dist: pymongo
Requires-Dist: twython
Requires-Dist: six
